secuuthJwtPythonSdk/__init__.py
secuuthJwtPythonSdk/accessToken.py
secuuthJwtPythonSdk/idToken.py
secuuthJwtPythonSdk-0.3.dist-info/LICENSE.txt
secuuthJwtPythonSdk-0.3.dist-info/METADATA
secuuthJwtPythonSdk-0.3.dist-info/WHEEL
secuuthJwtPythonSdk-0.3.dist-info/top_level.txt
secuuthJwtPythonSdk-0.3.dist-info/RECORD
